fs/dropboxfs/__init__.py
fs/dropboxfs/dropboxfs.py
fs/dropboxfs/opener.py
fs_dropboxfs-1.0.8.dist-info/METADATA
fs_dropboxfs-1.0.8.dist-info/WHEEL
fs_dropboxfs-1.0.8.dist-info/entry_points.txt
fs_dropboxfs-1.0.8.dist-info/licenses/LICENSE
fs_dropboxfs-1.0.8.dist-info/RECORD
