Metadata-Version: 2.4
Name: fs.dropboxfs
Version: 1.0.8
Summary: Pyfilesystem2 implementation for Dropbox
Project-URL: Homepage, https://github.com/rkhwaja/fs.dropboxfs
Maintainer-email: Rehan Khwaja <rehan@khwaja.name>
License-Expression: MIT
License-File: LICENSE
Keywords: Pyfilesystem2,dropbox,filesystem
Classifier: Development Status :: 5 - Production/Stable
Classifier: Intended Audience :: Developers
Classifier: Programming Language :: Python :: 3.8
Classifier: Programming Language :: Python :: 3.9
Classifier: Programming Language :: Python :: 3.10
Classifier: Programming Language :: Python :: 3.11
Classifier: Programming Language :: Python :: 3.12
Classifier: Programming Language :: Python :: 3.13
Classifier: Programming Language :: Python :: 3.14
Requires-Python: >=3.8
Requires-Dist: dropbox>=12.0.2
Requires-Dist: fs>=2.0.10
Requires-Dist: setuptools>=70
